GeeseTools/DataPreProcessor.py
GeeseTools/__init__.py
GeeseTools/create_bins_mixin.py
GeeseTools/datasets.py
GeeseTools/display_mixin.py
GeeseTools/drop_features_mixin.py
GeeseTools/drop_records_mixin.py
GeeseTools/encode_mixin.py
GeeseTools/feature_target_split_mixin.py
GeeseTools/feature_type_mixin.py
GeeseTools/impute_features_mixin.py
GeeseTools/missing_data_summary_mixin.py
GeeseTools/oversample_mixin.py
GeeseTools/pre_process_mixin.py
GeeseTools/sample_data_mixin.py
GeeseTools/scale_mixin.py
GeeseTools/split_dataframe_mixin.py
GeeseTools/to_numeric_mixin.py
GeeseTools/transform_mixin.py
GeeseTools/unique_value_summary_mixin.py
GeeseTools/Data/__init__.py
GeeseTools/Data/heart.csv
geesetools-0.2.1.dist-info/licenses/LICENSE
utils/__init__.py
utils/evaluate_classification.py
utils/evaluate_regression.py
utils/evaluation.py
utils/plot.py
utils/plot_classification_outputs.py
utils/plot_regression_outputs.py
utils/train_classification_model.py
utils/train_models.py
utils/train_regression_model.py
geesetools-0.2.1.dist-info/METADATA
geesetools-0.2.1.dist-info/WHEEL
geesetools-0.2.1.dist-info/top_level.txt
geesetools-0.2.1.dist-info/RECORD
