Metadata-Version: 2.4
Name: GeeseTools
Version: 0.2.1
Summary: Modular and extensible data preprocessing library
Author-email: Abhijeet <abhijeet1472@gmail.com>
Requires-Python: <3.12,>=3.9
License-File: LICENSE
Requires-Dist: pandas>=1.5
Requires-Dist: scikit-learn
Requires-Dist: imbalanced-learn
Requires-Dist: ipython
Requires-Dist: scipy
Requires-Dist: openpyxl
Requires-Dist: matplotlib
Requires-Dist: seaborn
Dynamic: license-file
